rtl/ppa/smoke/ppa_smoke.sv
`timescale 1ns/1ps

module ppa_smoke (
    input  wire        clk,
    input  wire        rst_n,
    input  wire        valid_i,
    input  wire [15:0] lhs_i,
    input  wire [15:0] rhs_i,
    input  wire [31:0] addend_i,
    output reg         valid_o,
    output reg  [31:0] result_o,
    output reg  [31:0] checksum_o
);
  reg [31:0] product_q;
  reg [31:0] addend_q;
  reg        valid_q;

  always @(posedge clk or negedge rst_n) begin
    if (!rst_n) begin
      product_q <= 32'd0;
      addend_q <= 32'd0;
      valid_q <= 1'b0;
      valid_o <= 1'b0;
      result_o <= 32'd0;
      checksum_o <= 32'd0;
    end else begin
      valid_q <= valid_i;
      if (valid_i) begin
        product_q <= lhs_i * rhs_i;
        addend_q <= addend_i;
      end
      valid_o <= valid_q;
      if (valid_q) begin
        result_o <= product_q + addend_q;
        checksum_o <= checksum_o ^ (product_q + addend_q);
      end
    end
  end
endmodule

rtl/ppa/smoke/tb_ppa_smoke.sv
`timescale 1ns/1ps

module tb_ppa_smoke;
  reg clk = 1'b0;
  reg rst_n = 1'b0;
  reg valid_i = 1'b0;
  reg [15:0] lhs_i = 16'd0;
  reg [15:0] rhs_i = 16'd0;
  reg [31:0] addend_i = 32'd0;
  wire valid_o;
  wire [31:0] result_o;
  wire [31:0] checksum_o;
  integer seen = 0;

  ppa_smoke dut (
      .clk(clk),
      .rst_n(rst_n),
      .valid_i(valid_i),
      .lhs_i(lhs_i),
      .rhs_i(rhs_i),
      .addend_i(addend_i),
      .valid_o(valid_o),
      .result_o(result_o),
      .checksum_o(checksum_o)
  );

  always #0.5 clk = ~clk;

  always @(posedge clk) begin
    if (valid_o) begin
      case (seen)
        0: if (result_o !== 32'd43) $fatal(1, "first result mismatch");
        1: if (result_o !== 32'd1235) $fatal(1, "second result mismatch");
        2: if (result_o !== 32'd262125) $fatal(1, "third result mismatch");
        default: $fatal(1, "unexpected result");
      endcase
      seen = seen + 1;
    end
  end

  initial begin
    $dumpfile("artifacts/environment/h197/ppa-smoke.vcd");
    $dumpvars(0, tb_ppa_smoke);
    repeat (3) @(posedge clk);
    rst_n <= 1'b1;
    @(posedge clk);
    valid_i <= 1'b1;
    lhs_i <= 16'd6;
    rhs_i <= 16'd7;
    addend_i <= 32'd1;
    @(posedge clk);
    lhs_i <= 16'd12;
    rhs_i <= 16'd100;
    addend_i <= 32'd35;
    @(posedge clk);
    lhs_i <= 16'd65535;
    rhs_i <= 16'd2;
    addend_i <= 32'd131055;
    @(posedge clk);
    valid_i <= 1'b0;
    lhs_i <= 16'd0;
    rhs_i <= 16'd0;
    addend_i <= 32'd0;
    repeat (4) @(posedge clk);
    if (seen != 3) $fatal(1, "result count mismatch");
    if (checksum_o !== (32'd43 ^ 32'd1235 ^ 32'd262125))
      $fatal(1, "checksum mismatch");
    $display("PPA_SMOKE_PASS checksum=%0d", checksum_o);
    $finish;
  end
endmodule

artifacts/environment/h197/ppa-smoke.vcd
$date
	Wed Aug 19 18:25:05 2026
$end
$version
	Icarus Verilog
$end
$timescale
	1ps
$end
$scope module tb_ppa_smoke $end
$var wire 1 ! valid_o $end
$var wire 32 " result_o [31:0] $end
$var wire 32 # checksum_o [31:0] $end
$var reg 32 $ addend_i [31:0] $end
$var reg 1 % clk $end
$var reg 16 & lhs_i [15:0] $end
$var reg 16 ' rhs_i [15:0] $end
$var reg 1 ( rst_n $end
$var reg 1 ) valid_i $end
$var integer 32 * seen [31:0] $end
$scope module dut $end
$var wire 32 + addend_i [31:0] $end
$var wire 1 % clk $end
$var wire 16 , lhs_i [15:0] $end
$var wire 16 - rhs_i [15:0] $end
$var wire 1 ( rst_n $end
$var wire 1 ) valid_i $end
$var reg 32 . addend_q [31:0] $end
$var reg 32 / checksum_o [31:0] $end
$var reg 32 0 product_q [31:0] $end
$var reg 32 1 result_o [31:0] $end
$var reg 1 ! valid_o $end
$var reg 1 2 valid_q $end
$upscope $end
$upscope $end
$enddefinitions $end
#0
$dumpvars
x2
bx 1
bx 0
bx /
bx .
b0 -
b0 ,
b0 +
b0 *
0)
0(
b0 '
b0 &
0%
b0 $
bx #
bx "
x!
$end
#500
b0 #
b0 /
b0 "
b0 1
0!
02
b0 .
b0 0
1%
#1000
0%
#1500
1%
#2000
0%
#2500
1(
1%
#3000
0%
#3500
b1 $
b1 +
b111 '
b111 -
b110 &
b110 ,
1)
1%
#4000
0%
#4500
b1 .
b101010 0
12
b100011 $
b100011 +
b1100100 '
b1100100 -
b1100 &
b1100 ,
1%
#5000
0%
#5500
b101011 #
b101011 /
b101011 "
b101011 1
1!
b100011 .
b10010110000 0
b11111111111101111 $
b11111111111101111 +
b10 '
b10 -
b1111111111111111 &
b1111111111111111 ,
1%
#6000
0%
#6500
b10011111000 #
b10011111000 /
b10011010011 "
b10011010011 1
b11111111111101111 .
b11111111111111110 0
b0 $
b0 +
b0 '
b0 -
b0 &
b0 ,
0)
b1 *
1%
#7000
0%
#7500
b111111101100010101 #
b111111101100010101 /
b111111111111101101 "
b111111111111101101 1
02
b10 *
1%
#8000
0%
#8500
0!
b11 *
1%
